embzip/__init__.py
embzip/core.py
embzip/setup.py
embzip/utils.py
embzip-0.2.0.dist-info/licenses/LICENSE
embzip-0.2.0.dist-info/METADATA
embzip-0.2.0.dist-info/WHEEL
embzip-0.2.0.dist-info/top_level.txt
embzip-0.2.0.dist-info/RECORD
