Metadata-Version: 2.4
Name: embzip
Version: 0.2.0
Summary: A tool for compressing and decompressing embeddings using Product Quantization
Author: embzip
Classifier: Programming Language :: Python :: 3
Classifier: License :: OSI Approved :: MIT License
Classifier: Operating System :: OS Independent
Requires-Python: >=3.6
License-File: LICENSE
Requires-Dist: torch
Requires-Dist: faiss-cpu
Dynamic: author
Dynamic: classifier
Dynamic: license-file
Dynamic: requires-dist
Dynamic: requires-python
Dynamic: summary
